more/babel_i18n/__init__.py
more/babel_i18n/app.py
more/babel_i18n/constants.py
more/babel_i18n/domain.py
more/babel_i18n/request_utils.py
more/babel_i18n/speaklater.py
more_babel_i18n-23.2.0.dist-info/LICENSE
more_babel_i18n-23.2.0.dist-info/METADATA
more_babel_i18n-23.2.0.dist-info/WHEEL
more_babel_i18n-23.2.0.dist-info/RECORD
